odoo/addons/product_assortment/README.rst
odoo/addons/product_assortment/__init__.py
odoo/addons/product_assortment/__manifest__.py
odoo/addons/product_assortment/i18n/es.po
odoo/addons/product_assortment/i18n/product_assortment.pot
odoo/addons/product_assortment/i18n/pt.po
odoo/addons/product_assortment/models/__init__.py
odoo/addons/product_assortment/models/ir_filters.py
odoo/addons/product_assortment/models/res_partner.py
odoo/addons/product_assortment/readme/CONTRIBUTORS.rst
odoo/addons/product_assortment/readme/DESCRIPTION.rst
odoo/addons/product_assortment/readme/HISTORY.rst
odoo/addons/product_assortment/readme/USAGE.rst
odoo/addons/product_assortment/static/description/icon.png
odoo/addons/product_assortment/static/description/index.html
odoo/addons/product_assortment/tests/__init__.py
odoo/addons/product_assortment/tests/test_product_assortment.py
odoo/addons/product_assortment/views/product_assortment.xml
odoo/addons/product_assortment/views/res_partner_view.xml
odoo12_addon_product_assortment-12.0.2.0.2.dist-info/METADATA
odoo12_addon_product_assortment-12.0.2.0.2.dist-info/WHEEL
odoo12_addon_product_assortment-12.0.2.0.2.dist-info/top_level.txt
odoo12_addon_product_assortment-12.0.2.0.2.dist-info/RECORD
