Metadata-Version: 2.1
Name: odoo12-addon-product-assortment
Version: 12.0.2.0.2
Summary: Adds the ability to manage products assortment
Home-page: https://github.com/OCA/product-attribute
Author: ACSONE SA/NV,Odoo Community Association (OCA)
Author-email: support@odoo-community.org
License: AGPL-3
Platform: UNKNOWN
Classifier: Programming Language :: Python
Classifier: Framework :: Odoo
Classifier: License :: OSI Approved :: GNU Affero General Public License v3
Classifier: Development Status :: 5 - Production/Stable
Requires-Python: >=3.5
Requires-Dist: odoo (<12.1dev,>=12.0a)
